{"generatedAt":"2026-01-15T17:26:07.295Z","source":"git","entries":{"":{"type":"dir","mtimeMs":1768497964793,"size":null},"404.html":{"type":"file","mtimeMs":1768491877535.9124,"size":1709},"docs":{"type":"dir","mtimeMs":1768497964847,"size":null},"docs/Curriculum-vitae-R.Cavdar.pdf":{"type":"file","mtimeMs":1768487317176.44,"size":170606},"docs/Onderzoeksverslag-van-R.Cavdar-20-01-2023.pdf":{"type":"file","mtimeMs":1768487317176.44,"size":577112},"docs/The-future-is-modular-R.Cavdar-06-11-2023.pdf":{"type":"file","mtimeMs":1768487317176.44,"size":610803},"images":{"type":"dir","mtimeMs":1768497964988,"size":null},"images/logo.png":{"type":"file","mtimeMs":1768487317176.44,"size":16554},"index.html":{"type":"file","mtimeMs":1768488338853.7273,"size":1850},"main.d.ts":{"type":"file","mtimeMs":1768494264938.9119,"size":830},"main.js":{"type":"file","mtimeMs":1768494264935.9124,"size":3183},"main.ts":{"type":"file","mtimeMs":1768491979680.802,"size":3792},"vendor":{"type":"dir","mtimeMs":1768497965221,"size":null},"vendor/bootstrap":{"type":"dir","mtimeMs":1768497965221,"size":null},"vendor/bootstrap/css":{"type":"dir","mtimeMs":1768497965222,"size":null},"vendor/bootstrap/css/bootstrap-grid.css":{"type":"file","mtimeMs":1768497962733.739,"size":70323},"vendor/bootstrap/css/bootstrap-grid.css.map":{"type":"file","mtimeMs":1768497962736.734,"size":203340},"vendor/bootstrap/css/bootstrap-grid.min.css":{"type":"file","mtimeMs":1768497962739.74,"size":51789},"vendor/bootstrap/css/bootstrap-grid.min.css.map":{"type":"file","mtimeMs":1768497962741.7395,"size":115912},"vendor/bootstrap/css/bootstrap-grid.rtl.css":{"type":"file","mtimeMs":1768497962744.7334,"size":70397},"vendor/bootstrap/css/bootstrap-grid.rtl.css.map":{"type":"file","mtimeMs":1768497962742.7395,"size":203344},"vendor/bootstrap/css/bootstrap-grid.rtl.min.css":{"type":"file","mtimeMs":1768497962745.7356,"size":51864},"vendor/bootstrap/css/bootstrap-grid.rtl.min.css.map":{"type":"file","mtimeMs":1768497962747.7366,"size":115989},"vendor/bootstrap/css/bootstrap-reboot.css":{"type":"file","mtimeMs":1768497962748.735,"size":12156},"vendor/bootstrap/css/bootstrap-reboot.css.map":{"type":"file","mtimeMs":1768497962750.7346,"size":129863},"vendor/bootstrap/css/bootstrap-reboot.min.css":{"type":"file","mtimeMs":1768497962749.7358,"size":10205},"vendor/bootstrap/css/bootstrap-reboot.min.css.map":{"type":"file","mtimeMs":1768497962752.7344,"size":51660},"vendor/bootstrap/css/bootstrap-reboot.rtl.css":{"type":"file","mtimeMs":1768497962753.735,"size":12149},"vendor/bootstrap/css/bootstrap-reboot.rtl.css.map":{"type":"file","mtimeMs":1768497962754.7368,"size":129878},"vendor/bootstrap/css/bootstrap-reboot.rtl.min.css":{"type":"file","mtimeMs":1768497962757.734,"size":10277},"vendor/bootstrap/css/bootstrap-reboot.rtl.min.css.map":{"type":"file","mtimeMs":1768497962755.736,"size":64328},"vendor/bootstrap/css/bootstrap-utilities.css":{"type":"file","mtimeMs":1768497962759.7388,"size":107938},"vendor/bootstrap/css/bootstrap-utilities.css.map":{"type":"file","mtimeMs":1768497962761.7378,"size":267983},"vendor/bootstrap/css/bootstrap-utilities.min.css":{"type":"file","mtimeMs":1768497962762.7356,"size":85457},"vendor/bootstrap/css/bootstrap-utilities.min.css.map":{"type":"file","mtimeMs":1768497962764.7368,"size":180636},"vendor/bootstrap/css/bootstrap-utilities.rtl.css":{"type":"file","mtimeMs":1768497962765.7368,"size":107806},"vendor/bootstrap/css/bootstrap-utilities.rtl.css.map":{"type":"file","mtimeMs":1768497962767.742,"size":267924},"vendor/bootstrap/css/bootstrap-utilities.rtl.min.css":{"type":"file","mtimeMs":1768497962769.7458,"size":85386},"vendor/bootstrap/css/bootstrap-utilities.rtl.min.css.map":{"type":"file","mtimeMs":1768497962773.7456,"size":180472},"vendor/bootstrap/css/bootstrap.css":{"type":"file","mtimeMs":1768497962774.7466,"size":280311},"vendor/bootstrap/css/bootstrap.css.map":{"type":"file","mtimeMs":1768497962771.7463,"size":680938},"vendor/bootstrap/css/bootstrap.min.css":{"type":"file","mtimeMs":1768497962776.7466,"size":232111},"vendor/bootstrap/css/bootstrap.min.css.map":{"type":"file","mtimeMs":1768497962778.7466,"size":590038},"vendor/bootstrap/css/bootstrap.rtl.css":{"type":"file","mtimeMs":1768497962780.7466,"size":279526},"vendor/bootstrap/css/bootstrap.rtl.css.map":{"type":"file","mtimeMs":1768497962782.8193,"size":680798},"vendor/bootstrap/css/bootstrap.rtl.min.css":{"type":"file","mtimeMs":1768497962783.8154,"size":232219},"vendor/bootstrap/css/bootstrap.rtl.min.css.map":{"type":"file","mtimeMs":1768497962785.8162,"size":589235},"vendor/bootstrap/js":{"type":"dir","mtimeMs":1768497966700,"size":null},"vendor/bootstrap/js/bootstrap.bundle.js":{"type":"file","mtimeMs":1768497962787.8147,"size":207836},"vendor/bootstrap/js/bootstrap.bundle.js.map":{"type":"file","mtimeMs":1768497962789.8186,"size":431870},"vendor/bootstrap/js/bootstrap.bundle.min.js":{"type":"file","mtimeMs":1768497962793.8145,"size":80496},"vendor/bootstrap/js/bootstrap.bundle.min.js.map":{"type":"file","mtimeMs":1768497962792.816,"size":332111},"vendor/bootstrap/js/bootstrap.esm.js":{"type":"file","mtimeMs":1768497962798.8296,"size":135902},"vendor/bootstrap/js/bootstrap.esm.js.map":{"type":"file","mtimeMs":1768497962795.818,"size":297005},"vendor/bootstrap/js/bootstrap.esm.min.js":{"type":"file","mtimeMs":1768497962796.8193,"size":73811},"vendor/bootstrap/js/bootstrap.esm.min.js.map":{"type":"file","mtimeMs":1768497962799.829,"size":222322},"vendor/bootstrap/js/bootstrap.js":{"type":"file","mtimeMs":1768497962802.8296,"size":145474},"vendor/bootstrap/js/bootstrap.js.map":{"type":"file","mtimeMs":1768497962804.83,"size":298167},"vendor/bootstrap/js/bootstrap.min.js":{"type":"file","mtimeMs":1768497962806.827,"size":60539},"vendor/bootstrap/js/bootstrap.min.js.map":{"type":"file","mtimeMs":1768497962807.8257,"size":220618},"_meta.json":{"type":"file","mtimeMs":1768497542669.8445,"size":5961}}}